calamancy/__init__.py
calamancy/inference.py
calamancy/loaders.py
calamanCy-0.2.2.dist-info/LICENSE
calamanCy-0.2.2.dist-info/METADATA
calamanCy-0.2.2.dist-info/WHEEL
calamanCy-0.2.2.dist-info/top_level.txt
calamanCy-0.2.2.dist-info/RECORD
