Metadata-Version: 2.2
Name: calamanCy
Version: 0.2.2
Summary: NLP Pipelines for Tagalog
Author-email: "Lj V. Miranda" <ljvmiranda@gmail.com>
License: MIT License
Project-URL: Repository, https://github.com/ljvmiranda921/calamanCy
Project-URL: Bug Tracker, https://github.com/ljvmiranda921/calamanCy/issues
Project-URL: Release Notes, https://github.com/ljvmiranda921/calamanCy/releases
Keywords: nlp,natural language processing,language technology,tagalog
Classifier: Development Status :: 3 - Alpha
Classifier: Intended Audience :: Science/Research
Classifier: Intended Audience :: Developers
Classifier: License :: OSI Approved :: MIT License
Classifier: Programming Language :: Python :: 3
Classifier: Programming Language :: Python :: 3.7
Classifier: Programming Language :: Python :: 3.8
Classifier: Programming Language :: Python :: 3.9
Classifier: Programming Language :: Python :: 3.10
Classifier: Topic :: Scientific/Engineering
Requires-Python: >=3.7
License-File: LICENSE
Requires-Dist: spacy>=3.5.0
Requires-Dist: wasabi>=0.9.1
Requires-Dist: typer>=0.4.2
Requires-Dist: spacy-transformers<=1.3.5,>=1.2.5
Provides-Extra: dev
Requires-Dist: black>=23.1.0; extra == "dev"
Requires-Dist: isort>=5.0.0; extra == "dev"
Requires-Dist: ruff>=0.0.272; extra == "dev"
Requires-Dist: mypy>=1.0.0; extra == "dev"
Requires-Dist: pytest; extra == "dev"
